{"comparisons": ["IRW_vs_CW", "con_vs_CW", "con_vs_IRW", "IR_vs_IRW"], "direction": "both", "intersection_genes_count": 146, "gene_set": "GO_Biological_Process", "organism": "Mouse", "data": [{"Gene_set": "GO_Biological_Process.gmt", "Term": "GOBP_B_CELL_MEDIATED_IMMUNITY", "Overlap": "14/274", "P-value": 4.18909202960391e-08, "Adjusted P-value": 6.836598192313582e-05, "Odds Ratio": null, "Combined Score": null, "Genes": "Clcf1;Ighv1-12;Ighv1-4;Ighv1-61;Ighv1-69;Ighv1-72;Ighv1-76;Ighv1-78;Ighv1-84;Ighv14-2;Ighv2-2;Ighv3-1;Ighv7-3;Ighv8-5"}, {"Gene_set": "GO_Biological_Process.gmt", "Term": "GOBP_LYMPHOCYTE_MEDIATED_IMMUNITY", "Overlap": "16/468", "P-value": 1.0579189200195378e-06, "Adjusted P-value": 0.0008632618387359428, "Odds Ratio": null, "Combined Score": null, "Genes": "Clcf1;Fosl2;Ighv1-12;Ighv1-4;Ighv1-61;Ighv1-69;Ighv1-72;Ighv1-76;Ighv1-78;Ighv1-84;Ighv14-2;Ighv2-2;Ighv3-1;Ighv7-3;Ighv8-5;Smad7"}, {"Gene_set": "GO_Biological_Process.gmt", "Term": "GOBP_ADAPTIVE_IMMUNE_RESPONSE_BASED_ON_SOMATIC_RECOMBINATION_OF_IMMUNE_RECEPTORS_BUILT_FROM_IMMUNOGLOBULIN_SUPERFAMILY_DOMAINS", "Overlap": "16/484", "P-value": 1.6393838162988392e-06, "Adjusted P-value": 0.0008918247960665685, "Odds Ratio": null, "Combined Score": null, "Genes": "Clcf1;Fosl2;Ighv1-12;Ighv1-4;Ighv1-61;Ighv1-69;Ighv1-72;Ighv1-76;Ighv1-78;Ighv1-84;Ighv14-2;Ighv2-2;Ighv3-1;Ighv7-3;Ighv8-5;Smad7"}, {"Gene_set": "GO_Biological_Process.gmt", "Term": "GOBP_LEUKOCYTE_MEDIATED_IMMUNITY", "Overlap": "17/585", "P-value": 4.339129844055278e-06, "Adjusted P-value": 0.0017703649763745534, "Odds Ratio": null, "Combined Score": null, "Genes": "Clcf1;Fosl2;Ighv1-12;Ighv1-4;Ighv1-61;Ighv1-69;Ighv1-72;Ighv1-76;Ighv1-78;Ighv1-84;Ighv14-2;Ighv2-2;Ighv3-1;Ighv7-3;Ighv8-5;Nr4a3;Smad7"}, {"Gene_set": "GO_Biological_Process.gmt", "Term": "GOBP_PRODUCTION_OF_MOLECULAR_MEDIATOR_OF_IMMUNE_RESPONSE", "Overlap": "13/400", "P-value": 1.9506088614726792e-05, "Adjusted P-value": 0.006366787323846825, "Odds Ratio": null, "Combined Score": null, "Genes": "Clcf1;Fosl2;Igkv1-122;Igkv1-133;Igkv12-89;Igkv3-2;Igkv3-5;Igkv4-58;Igkv4-90;Igkv5-37;Igkv6-13;Nr4a3;Smad7"}, {"Gene_set": "GO_Biological_Process.gmt", "Term": "GOBP_IMMUNOGLOBULIN_PRODUCTION", "Overlap": "10/251", "P-value": 3.3891005633921306e-05, "Adjusted P-value": 0.009218353532426596, "Odds Ratio": null, "Combined Score": null, "Genes": "Clcf1;Igkv1-122;Igkv1-133;Igkv12-89;Igkv3-2;Igkv3-5;Igkv4-58;Igkv4-90;Igkv5-37;Igkv6-13"}, {"Gene_set": "GO_Biological_Process.gmt", "Term": "GOBP_ADAPTIVE_IMMUNE_RESPONSE", "Overlap": "16/630", "P-value": 4.379886561086914e-05, "Adjusted P-value": 0.009673268744700031, "Odds Ratio": null, "Combined Score": null, "Genes": "Clcf1;Fosl2;Ighv1-12;Ighv1-4;Ighv1-61;Ighv1-69;Ighv1-72;Ighv1-76;Ighv1-78;Ighv1-84;Ighv14-2;Ighv2-2;Ighv3-1;Ighv7-3;Ighv8-5;Smad7"}, {"Gene_set": "GO_Biological_Process.gmt", "Term": "GOBP_IMMUNE_EFFECTOR_PROCESS", "Overlap": "19/851", "P-value": 4.741798404264721e-05, "Adjusted P-value": 0.009673268744700031, "Odds Ratio": null, "Combined Score": null, "Genes": "Clcf1;Fosl2;Ighv1-12;Ighv1-4;Ighv1-61;Ighv1-69;Ighv1-72;Ighv1-76;Ighv1-78;Ighv1-84;Ighv14-2;Ighv2-2;Ighv3-1;Ighv7-3;Ighv8-5;Lgals1;Nr4a3;Pglyrp1;Smad7"}, {"Gene_set": "GO_Biological_Process.gmt", "Term": "GOBP_POSITIVE_REGULATION_OF_FIBROBLAST_GROWTH_FACTOR_PRODUCTION", "Overlap": "2/6", "P-value": 0.0009273436903429684, "Adjusted P-value": 0.16815832251552493, "Odds Ratio": null, "Combined Score": null, "Genes": "Aif1;Ptgs2"}, {"Gene_set": "GO_Biological_Process.gmt", "Term": "GOBP_FORMATION_OF_PRIMARY_GERM_LAYER", "Overlap": "5/109", "P-value": 0.0018080239024409737, "Adjusted P-value": 0.2950695008783669, "Odds Ratio": null, "Combined Score": null, "Genes": "Dusp4;Dusp5;Epha2;Macf1;Nr4a3"}, {"Gene_set": "GO_Biological_Process.gmt", "Term": "GOBP_FAT_PAD_DEVELOPMENT", "Overlap": "2/10", "P-value": 0.002724338983898017, "Adjusted P-value": 0.404192838338324, "Odds Ratio": null, "Combined Score": null, "Genes": "Arrdc3;Fosl2"}, {"Gene_set": "GO_Biological_Process.gmt", "Term": "GOBP_FIBROBLAST_GROWTH_FACTOR_PRODUCTION", "Overlap": "2/11", "P-value": 0.0033123763652662124, "Adjusted P-value": 0.4504831856762049, "Odds Ratio": null, "Combined Score": null, "Genes": "Aif1;Ptgs2"}, {"Gene_set": "GO_Biological_Process.gmt", "Term": "GOBP_CELLULAR_RESPONSE_TO_COPPER_ION", "Overlap": "2/14", "P-value": 0.005395255711333222, "Adjusted P-value": 0.6773121016073707, "Odds Ratio": null, "Combined Score": null, "Genes": "Atp7b;Mt1"}, {"Gene_set": "GO_Biological_Process.gmt", "Term": "GOBP_POSITIVE_REGULATION_OF_HOMOTYPIC_CELL_CELL_ADHESION", "Overlap": "2/16", "P-value": 0.007040791663815516, "Adjusted P-value": 0.8207551425247802, "Odds Ratio": null, "Combined Score": null, "Genes": "Lgals1;Plaur"}, {"Gene_set": "GO_Biological_Process.gmt", "Term": "GOBP_REGULATION_OF_HEAT_GENERATION", "Overlap": "2/17", "P-value": 0.007938091790961192, "Adjusted P-value": 0.8343697740016005, "Odds Ratio": null, "Combined Score": null, "Genes": "Arrdc3;Ptgs2"}, {"Gene_set": "GO_Biological_Process.gmt", "Term": "GOBP_REGULATION_OF_TYPE_B_PANCREATIC_CELL_PROLIFERATION", "Overlap": "2/18", "P-value": 0.008883969108305275, "Adjusted P-value": 0.8343697740016005, "Odds Ratio": null, "Combined Score": null, "Genes": "Nr4a1;Nr4a3"}, {"Gene_set": "GO_Biological_Process.gmt", "Term": "GOBP_CELL_MIGRATION_INVOLVED_IN_SPROUTING_ANGIOGENESIS", "Overlap": "3/55", "P-value": 0.009624318319200098, "Adjusted P-value": 0.8343697740016005, "Odds Ratio": null, "Combined Score": null, "Genes": "Nr4a1;Plk2;Ptgs2"}, {"Gene_set": "GO_Biological_Process.gmt", "Term": "GOBP_POSITIVE_REGULATION_OF_CELL_MIGRATION_INVOLVED_IN_SPROUTING_ANGIOGENESIS", "Overlap": "2/22", "P-value": 0.013136982829605489, "Adjusted P-value": 0.8343697740016005, "Odds Ratio": null, "Combined Score": null, "Genes": "Plk2;Ptgs2"}, {"Gene_set": "GO_Biological_Process.gmt", "Term": "GOBP_POSITIVE_REGULATION_OF_SMOOTH_MUSCLE_CELL_PROLIFERATION", "Overlap": "4/117", "P-value": 0.01435965201155427, "Adjusted P-value": 0.8343697740016005, "Odds Ratio": null, "Combined Score": null, "Genes": "Aif1;Nr4a3;Ptgs2;S1pr1"}, {"Gene_set": "GO_Biological_Process.gmt", "Term": "GOBP_NEGATIVE_REGULATION_OF_LYMPHOCYTE_DIFFERENTIATION", "Overlap": "3/64", "P-value": 0.014513033191624268, "Adjusted P-value": 0.8343697740016005, "Odds Ratio": null, "Combined Score": null, "Genes": "Pglyrp1;Smad7;Zfp608"}, {"Gene_set": "GO_Biological_Process.gmt", "Term": "GOBP_HEAT_GENERATION", "Overlap": "2/24", "P-value": 0.015534076721815612, "Adjusted P-value": 0.8343697740016005, "Odds Ratio": null, "Combined Score": null, "Genes": "Arrdc3;Ptgs2"}, {"Gene_set": "GO_Biological_Process.gmt", "Term": "GOBP_RESPONSE_TO_FLUID_SHEAR_STRESS", "Overlap": "2/24", "P-value": 0.015534076721815612, "Adjusted P-value": 0.8343697740016005, "Odds Ratio": null, "Combined Score": null, "Genes": "Abca1;Ptgs2"}, {"Gene_set": "GO_Biological_Process.gmt", "Term": "GOBP_RESPONSE_TO_COPPER_ION", "Overlap": "2/25", "P-value": 0.016797558134792834, "Adjusted P-value": 0.8343697740016005, "Odds Ratio": null, "Combined Score": null, "Genes": "Atp7b;Mt1"}, {"Gene_set": "GO_Biological_Process.gmt", "Term": "GOBP_OSSIFICATION", "Overlap": "9/491", "P-value": 0.017022455382925974, "Adjusted P-value": 0.8343697740016005, "Odds Ratio": null, "Combined Score": null, "Genes": "Asxl2;Clec5a;Crim1;Epha2;Fosl2;Mn1;Ptgs2;S1pr1;Smad7"}, {"Gene_set": "GO_Biological_Process.gmt", "Term": "GOBP_GASTRULATION", "Overlap": "5/188", "P-value": 0.017462762627520147, "Adjusted P-value": 0.8343697740016005, "Odds Ratio": null, "Combined Score": null, "Genes": "Dusp4;Dusp5;Epha2;Macf1;Nr4a3"}, {"Gene_set": "GO_Biological_Process.gmt", "Term": "GOBP_BLOOD_VESSEL_ENDOTHELIAL_CELL_MIGRATION", "Overlap": "4/126", "P-value": 0.01835941283118015, "Adjusted P-value": 0.8343697740016005, "Odds Ratio": null, "Combined Score": null, "Genes": "Epha2;Nr4a1;Plk2;Ptgs2"}, {"Gene_set": "GO_Biological_Process.gmt", "Term": "GOBP_MESODERM_MORPHOGENESIS", "Overlap": "3/72", "P-value": 0.01984308731035231, "Adjusted P-value": 0.8343697740016005, "Odds Ratio": null, "Combined Score": null, "Genes": "Epha2;Macf1;Nr4a3"}, {"Gene_set": "GO_Biological_Process.gmt", "Term": "GOBP_ADIPOSE_TISSUE_DEVELOPMENT", "Overlap": "3/73", "P-value": 0.020575378639506738, "Adjusted P-value": 0.8343697740016005, "Odds Ratio": null, "Combined Score": null, "Genes": "Arrdc3;Fosl2;Selenom"}, {"Gene_set": "GO_Biological_Process.gmt", "Term": "GOBP_NEGATIVE_REGULATION_OF_CYSTEINE_TYPE_ENDOPEPTIDASE_ACTIVITY", "Overlap": "3/73", "P-value": 0.020575378639506738, "Adjusted P-value": 0.8343697740016005, "Odds Ratio": null, "Combined Score": null, "Genes": "Nr4a1;Plaur;Ptgs2"}, {"Gene_set": "GO_Biological_Process.gmt", "Term": "GOBP_CHONDROCYTE_PROLIFERATION", "Overlap": "2/28", "P-value": 0.020838719917695692, "Adjusted P-value": 0.8343697740016005, "Odds Ratio": null, "Combined Score": null, "Genes": "Fosl2;Smad7"}, {"Gene_set": "GO_Biological_Process.gmt", "Term": "GOBP_DETECTION_OF_EXTERNAL_BIOTIC_STIMULUS", "Overlap": "2/28", "P-value": 0.020838719917695692, "Adjusted P-value": 0.8343697740016005, "Odds Ratio": null, "Combined Score": null, "Genes": "Nr4a1;Pglyrp1"}, {"Gene_set": "GO_Biological_Process.gmt", "Term": "GOBP_INTRACELLULAR_ZINC_ION_HOMEOSTASIS", "Overlap": "2/28", "P-value": 0.020838719917695692, "Adjusted P-value": 0.8343697740016005, "Odds Ratio": null, "Combined Score": null, "Genes": "Atp7b;Mt1"}, {"Gene_set": "GO_Biological_Process.gmt", "Term": "GOBP_SPROUTING_ANGIOGENESIS", "Overlap": "4/135", "P-value": 0.022989427243219385, "Adjusted P-value": 0.8343697740016005, "Odds Ratio": null, "Combined Score": null, "Genes": "Epha2;Nr4a1;Plk2;Ptgs2"}, {"Gene_set": "GO_Biological_Process.gmt", "Term": "GOBP_BONE_MINERALIZATION", "Overlap": "4/141", "P-value": 0.026437053501015963, "Adjusted P-value": 0.8343697740016005, "Odds Ratio": null, "Combined Score": null, "Genes": "Asxl2;Fosl2;Ptgs2;S1pr1"}, {"Gene_set": "GO_Biological_Process.gmt", "Term": "GOBP_PEPTIDYL_TYROSINE_DEPHOSPHORYLATION", "Overlap": "2/34", "P-value": 0.02998404724092723, "Adjusted P-value": 0.8343697740016005, "Odds Ratio": null, "Combined Score": null, "Genes": "Dusp4;Dusp5"}, {"Gene_set": "GO_Biological_Process.gmt", "Term": "GOBP_REGULATION_OF_HOMOTYPIC_CELL_CELL_ADHESION", "Overlap": "2/37", "P-value": 0.03505060609507767, "Adjusted P-value": 0.8343697740016005, "Odds Ratio": null, "Combined Score": null, "Genes": "Lgals1;Plaur"}, {"Gene_set": "GO_Biological_Process.gmt", "Term": "GOBP_DETECTION_OF_BIOTIC_STIMULUS", "Overlap": "2/38", "P-value": 0.03680816906722465, "Adjusted P-value": 0.8343697740016005, "Odds Ratio": null, "Combined Score": null, "Genes": "Nr4a1;Pglyrp1"}, {"Gene_set": "GO_Biological_Process.gmt", "Term": "GOBP_TYPE_B_PANCREATIC_CELL_PROLIFERATION", "Overlap": "2/38", "P-value": 0.03680816906722465, "Adjusted P-value": 0.8343697740016005, "Odds Ratio": null, "Combined Score": null, "Genes": "Nr4a1;Nr4a3"}, {"Gene_set": "GO_Biological_Process.gmt", "Term": "GOBP_REGULATION_OF_RESPONSE_TO_NUTRIENT_LEVELS", "Overlap": "2/39", "P-value": 0.038599009744765246, "Adjusted P-value": 0.8343697740016005, "Odds Ratio": null, "Combined Score": null, "Genes": "Gdf15;Mn1"}, {"Gene_set": "GO_Biological_Process.gmt", "Term": "GOBP_AXIAL_MESODERM_MORPHOGENESIS", "Overlap": "1/5", "P-value": 0.039238161524353006, "Adjusted P-value": 0.8343697740016005, "Odds Ratio": null, "Combined Score": null, "Genes": "Epha2"}, {"Gene_set": "GO_Biological_Process.gmt", "Term": "GOBP_GROWTH_INVOLVED_IN_HEART_MORPHOGENESIS", "Overlap": "1/5", "P-value": 0.039238161524353006, "Adjusted P-value": 0.8343697740016005, "Odds Ratio": null, "Combined Score": null, "Genes": "S1pr1"}, {"Gene_set": "GO_Biological_Process.gmt", "Term": "GOBP_NEGATIVE_REGULATION_OF_ADENYLATE_CYCLASE_ACTIVATING_ADRENERGIC_RECEPTOR_SIGNALING_PATHWAY", "Overlap": "1/5", "P-value": 0.039238161524353006, "Adjusted P-value": 0.8343697740016005, "Odds Ratio": null, "Combined Score": null, "Genes": "Arrdc3"}, {"Gene_set": "GO_Biological_Process.gmt", "Term": "GOBP_NEGATIVE_REGULATION_OF_SMOOTH_MUSCLE_CELL_CHEMOTAXIS", "Overlap": "1/5", "P-value": 0.039238161524353006, "Adjusted P-value": 0.8343697740016005, "Odds Ratio": null, "Combined Score": null, "Genes": "Aif1"}, {"Gene_set": "GO_Biological_Process.gmt", "Term": "GOBP_NOTOCHORD_FORMATION", "Overlap": "1/5", "P-value": 0.039238161524353006, "Adjusted P-value": 0.8343697740016005, "Odds Ratio": null, "Combined Score": null, "Genes": "Epha2"}, {"Gene_set": "GO_Biological_Process.gmt", "Term": "GOBP_NUCLEAR_MIGRATION_ALONG_MICROTUBULE", "Overlap": "1/5", "P-value": 0.039238161524353006, "Adjusted P-value": 0.8343697740016005, "Odds Ratio": null, "Combined Score": null, "Genes": "Syne2"}, {"Gene_set": "GO_Biological_Process.gmt", "Term": "GOBP_POSITIVE_REGULATION_OF_MAST_CELL_CYTOKINE_PRODUCTION", "Overlap": "1/5", "P-value": 0.039238161524353006, "Adjusted P-value": 0.8343697740016005, "Odds Ratio": null, "Combined Score": null, "Genes": "Nr4a3"}, {"Gene_set": "GO_Biological_Process.gmt", "Term": "GOBP_POSITIVE_REGULATION_OF_SMOOTH_MUSCLE_CELL_CHEMOTAXIS", "Overlap": "1/5", "P-value": 0.039238161524353006, "Adjusted P-value": 0.8343697740016005, "Odds Ratio": null, "Combined Score": null, "Genes": "Aif1"}, {"Gene_set": "GO_Biological_Process.gmt", "Term": "GOBP_POSITIVE_REGULATION_OF_VITAMIN_D_RECEPTOR_SIGNALING_PATHWAY", "Overlap": "1/5", "P-value": 0.039238161524353006, "Adjusted P-value": 0.8343697740016005, "Odds Ratio": null, "Combined Score": null, "Genes": "Mn1"}, {"Gene_set": "GO_Biological_Process.gmt", "Term": "GOBP_REGULATION_OF_CORTICOTROPIN_RELEASING_HORMONE_SECRETION", "Overlap": "1/5", "P-value": 0.039238161524353006, "Adjusted P-value": 0.8343697740016005, "Odds Ratio": null, "Combined Score": null, "Genes": "Clcf1"}, {"Gene_set": "GO_Biological_Process.gmt", "Term": "GOBP_REGULATION_OF_NATURAL_KILLER_CELL_DIFFERENTIATION_INVOLVED_IN_IMMUNE_RESPONSE", "Overlap": "1/5", "P-value": 0.039238161524353006, "Adjusted P-value": 0.8343697740016005, "Odds Ratio": null, "Combined Score": null, "Genes": "Pglyrp1"}]}